mdslicer/__init__.py
mdslicer/mdslicer.py
mdslicer-0.3.1.dist-info/licenses/LICENSE
mdslicer-0.3.1.dist-info/METADATA
mdslicer-0.3.1.dist-info/WHEEL
mdslicer-0.3.1.dist-info/entry_points.txt
mdslicer-0.3.1.dist-info/top_level.txt
mdslicer-0.3.1.dist-info/RECORD
