Metadata-Version: 2.4
Name: mdslicer
Version: 0.3.1
Summary: A library to slice a markdown file into HTML sections.
Author-email: Matthieu Boileau <matthieu.boileau@math.unistra.fr>
License: MIT
Project-URL: Homepage, https://github.com/boileaum/mdslicer
Classifier: Programming Language :: Python :: 3
Classifier: License :: OSI Approved :: MIT License
Classifier: Operating System :: OS Independent
Requires-Python: >=3.8
License-File: LICENSE
Requires-Dist: python-frontmatter
Requires-Dist: bs4
Requires-Dist: markdown
Provides-Extra: test
Requires-Dist: pytest; extra == "test"
Requires-Dist: pytest-cov; extra == "test"
Requires-Dist: faker; extra == "test"
Provides-Extra: doc
Requires-Dist: Sphinx>=7.2.2; extra == "doc"
Requires-Dist: myst-parser; extra == "doc"
Requires-Dist: furo; extra == "doc"
Requires-Dist: sphinx-copybutton; extra == "doc"
Requires-Dist: sphinx-autobuild; extra == "doc"
Requires-Dist: sphinx-autodoc-typehints; extra == "doc"
Dynamic: license-file
